pairasync/__init__.py
pairasync/pairasync.py
pairasync/py.typed
pairasync-1.0.1.dist-info/METADATA
pairasync-1.0.1.dist-info/WHEEL
pairasync-1.0.1.dist-info/licenses/LICENSE
pairasync-1.0.1.dist-info/RECORD
