Metadata-Version: 2.3
Name: pairasync
Version: 1.0.1
Summary: Pair async code to your sync code
Author: Aaron2599
Requires-Python: >=3.8
